dash_deckgl/DashDeckgl.py
dash_deckgl/__init__.py
dash_deckgl/_imports_.py
dash_deckgl/dash_deckgl.min.js
dash_deckgl/deckgl.js
dash_deckgl/metadata.json
dash_deckgl/package-info.json
dash_deckgl/vendor.js
dash_deckgl-0.9.1.dist-info/LICENSE
dash_deckgl-0.9.1.dist-info/METADATA
dash_deckgl-0.9.1.dist-info/WHEEL
dash_deckgl-0.9.1.dist-info/top_level.txt
dash_deckgl-0.9.1.dist-info/RECORD
