Metadata-Version: 2.2
Name: dash_deckgl
Version: 0.9.1
Summary: Deck.gl component for Dash
Author: Oceanum developers <developers@oceanum.science>
License: MIT
Classifier: Framework :: Dash
License-File: LICENSE
Dynamic: author
Dynamic: classifier
Dynamic: description
Dynamic: description-content-type
Dynamic: license
Dynamic: summary
